hlmm/__init__.py
hlmm/hetlm.py
hlmm/hetlmm.py
hlmm-1.3.0a1.data/scripts/hlmm_chr.py
hlmm-1.3.0a1.dist-info/DESCRIPTION.rst
hlmm-1.3.0a1.dist-info/METADATA
hlmm-1.3.0a1.dist-info/RECORD
hlmm-1.3.0a1.dist-info/WHEEL
hlmm-1.3.0a1.dist-info/metadata.json
hlmm-1.3.0a1.dist-info/top_level.txt
