Metadata-Version: 2.0
Name: hlmm
Version: 1.3.0a1
Summary: Functions for fitting heteroskedastic linear (mixed) models to genetic data
Home-page: http://github.com/alexTISYoung/hlmm
Author: Alexander I. Young
Author-email: alextisyoung@gmail.com
License: MIT
Download-URL: https://github.com/AlexTISYoung/hlmm/archive/1.2.0a1.tar.gz
Keywords: statistics genetics heteroskedastic linear mixed model
Platform: UNKNOWN
Classifier: Development Status :: 3 - Alpha
Classifier: Intended Audience :: Science/Research
Classifier: Topic :: Scientific/Engineering :: Bio-Informatics
Classifier: License :: OSI Approved :: MIT License
Classifier: Programming Language :: Python :: 2.7
Requires-Dist: numpy
Requires-Dist: pysnptools
Requires-Dist: scipy
Provides-Extra: test
Requires-Dist: numdifftools; extra == 'test'
